CHANGES.txt
LICENSE.txt
MANIFEST.in
README.txt
netapp.config.maker.Config.tmpl
netapp.config.maker.RC.tmpl
netapp.config.maker.py
netapp.config.maker.py3
setup.py
docs/ConfigExample.xml
docs/HOWTO.txt
netappConfigMaker.egg-info/PKG-INFO
netappConfigMaker.egg-info/SOURCES.txt
netappConfigMaker.egg-info/dependency_links.txt
netappConfigMaker.egg-info/requires.txt
netappConfigMaker.egg-info/top_level.txt