Metadata-Version: 1.1
Name: netappConfigMaker
Version: 1.5.5
Summary: Netapp 7Mode Configuration generator based on a XML configuration file.
Home-page: http://pypi.python.org/pypi/netappConfigMaker/
Author: Shah Mohsin WAHED
Author-email: shahmohsin.wahed@gmail.com
License: LICENSE.txt
Keywords: netapp 7mode 7M configuration generator script
Platform: UNKNOWN
Classifier: Development Status :: 5 - Production/Stable
Classifier: Environment :: Console
Classifier: Intended Audience :: System Administrators
Classifier: License :: OSI Approved :: GNU General Public License v3 (GPLv3)
Classifier: Operating System :: POSIX :: Linux
Classifier: Operating System :: POSIX
Classifier: Programming Language :: Python :: 2.7
Classifier: Programming Language :: Python :: 3
Classifier: Topic :: System
Classifier: Topic :: System :: Hardware
Classifier: Topic :: System :: Installation/Setup
Classifier: Topic :: System :: Systems Administration
Classifier: Topic :: Utilities
